alibabacloud_elasticsearch20170613/__init__.py
alibabacloud_elasticsearch20170613/client.py
alibabacloud_elasticsearch20170613/models/__init__.py
alibabacloud_elasticsearch20170613/models/_activate_zones_request.py
alibabacloud_elasticsearch20170613/models/_activate_zones_response.py
alibabacloud_elasticsearch20170613/models/_activate_zones_response_body.py
alibabacloud_elasticsearch20170613/models/_add_connectable_cluster_request.py
alibabacloud_elasticsearch20170613/models/_add_connectable_cluster_response.py
alibabacloud_elasticsearch20170613/models/_add_connectable_cluster_response_body.py
alibabacloud_elasticsearch20170613/models/_add_snapshot_repo_request.py
alibabacloud_elasticsearch20170613/models/_add_snapshot_repo_response.py
alibabacloud_elasticsearch20170613/models/_add_snapshot_repo_response_body.py
alibabacloud_elasticsearch20170613/models/_cancel_deletion_request.py
alibabacloud_elasticsearch20170613/models/_cancel_deletion_response.py
alibabacloud_elasticsearch20170613/models/_cancel_deletion_response_body.py
alibabacloud_elasticsearch20170613/models/_cancel_logstash_deletion_request.py
alibabacloud_elasticsearch20170613/models/_cancel_logstash_deletion_response.py
alibabacloud_elasticsearch20170613/models/_cancel_logstash_deletion_response_body.py
alibabacloud_elasticsearch20170613/models/_cancel_task_request.py
alibabacloud_elasticsearch20170613/models/_cancel_task_response.py
alibabacloud_elasticsearch20170613/models/_cancel_task_response_body.py
alibabacloud_elasticsearch20170613/models/_capacity_plan_request.py
alibabacloud_elasticsearch20170613/models/_capacity_plan_response.py
alibabacloud_elasticsearch20170613/models/_capacity_plan_response_body.py
alibabacloud_elasticsearch20170613/models/_client_node_configuration.py
alibabacloud_elasticsearch20170613/models/_close_diagnosis_request.py
alibabacloud_elasticsearch20170613/models/_close_diagnosis_response.py
alibabacloud_elasticsearch20170613/models/_close_diagnosis_response_body.py
alibabacloud_elasticsearch20170613-5.0.2.dist-info/LICENSE
alibabacloud_elasticsearch20170613-5.0.2.dist-info/METADATA
alibabacloud_elasticsearch20170613-5.0.2.dist-info/WHEEL
alibabacloud_elasticsearch20170613-5.0.2.dist-info/top_level.txt
alibabacloud_elasticsearch20170613-5.0.2.dist-info/RECORD
